funflow/__init__.py
funflow/functional.py
funflow/grid_map.py
funflow/layer.py
funflow/map.py
funflow/model.py
funflow/rename.py
funflow/tag_filter.py
funflow/tags.py
funflow/template_engine.py
funflow/template_engine_old.py
funflow/template_utils.py
funflow/template_utils_old.py
funflow/templates.py
funflow/templates_old.py
funflow-0.0.2.dist-info/LICENSE
funflow-0.0.2.dist-info/METADATA
funflow-0.0.2.dist-info/WHEEL
funflow-0.0.2.dist-info/top_level.txt
funflow-0.0.2.dist-info/RECORD
